CHANGELOG.md
green_eggs/__init__.py
green_eggs/api/__init__.py
green_eggs/api/common.py
green_eggs/api/direct.py
green_eggs/bot.py
green_eggs/channel.py
green_eggs/client.py
green_eggs/commands/__init__.py
green_eggs/commands/registry.py
green_eggs/commands/triggers.py
green_eggs/config.py
green_eggs/constants.py
green_eggs/data_types.py
green_eggs/exceptions.py
green_eggs/types.py
green_eggs/utils.py
green_eggs-0.3.0.dist-info/LICENSE
green_eggs-0.3.0.dist-info/WHEEL
green_eggs-0.3.0.dist-info/METADATA
green_eggs-0.3.0.dist-info/RECORD
