Metadata-Version: 2.1
Name: green-eggs
Version: 0.3.0
Summary: A framework to build a Twitch chatbot.
Home-page: https://github.com/hamstap85/green-eggs/
License: ISC
Keywords: Twitch,chatbot,async
Author: Hameed Gifford
Author-email: giff.h92@gmail.com
Requires-Python: >=3.7,<4.0
Classifier: Development Status :: 2 - Pre-Alpha
Classifier: Framework :: AsyncIO
Classifier: Intended Audience :: Developers
Classifier: License :: OSI Approved
Classifier: License :: OSI Approved :: ISC License (ISCL)
Classifier: Operating System :: OS Independent
Classifier: Programming Language :: Python
Classifier: Programming Language :: Python :: 3
Classifier: Programming Language :: Python :: 3 :: Only
Classifier: Programming Language :: Python :: 3.10
Classifier: Programming Language :: Python :: 3.7
Classifier: Programming Language :: Python :: 3.8
Classifier: Programming Language :: Python :: 3.9
Classifier: Topic :: Software Development :: Libraries :: Python Modules
Classifier: Typing :: Typed
Requires-Dist: aiohttp[speedups] (>=3.8.1,<4.0.0)
Requires-Dist: aiologger[aiofiles] (>=0.6.1,<0.7.0)
Requires-Dist: asyncstdlib (>=3.10.3,<4.0.0)
Requires-Dist: websockets (>=10.1,<11.0)
Project-URL: Repository, https://github.com/hamstap85/green-eggs/
